fastdbc/__init__.py
fastdbc/__main__.py
fastdbc-0.1.0.dist-info/entry_points.txt
fastdbc-0.1.0.dist-info/METADATA
fastdbc-0.1.0.dist-info/WHEEL
fastdbc-0.1.0.dist-info/RECORD
