Metadata-Version: 2.1
Name: fastdbc
Version: 0.1.0
Summary: 
Author: wanqiang.liu
Author-email: wanqiang.liu@freetech.com
Requires-Python: >=3.10,<4.0
Classifier: Programming Language :: Python :: 3
Classifier: Programming Language :: Python :: 3.10
Classifier: Programming Language :: Python :: 3.11
Requires-Dist: typer[all] (>=0.7.0,<0.8.0)
